sigpropy/__init__.py
sigpropy/fouriertransform.py
sigpropy/fouriertransformsuite.py
sigpropy/meta.py
sigpropy/timeseries.py
sigpropy/windowedtimeseries.py
sigpropy-1.0.0.dist-info/LICENSE.txt
sigpropy-1.0.0.dist-info/METADATA
sigpropy-1.0.0.dist-info/WHEEL
sigpropy-1.0.0.dist-info/top_level.txt
sigpropy-1.0.0.dist-info/RECORD
