Metadata-Version: 2.1
Name: sigpropy
Version: 1.0.0
Summary: A Python package for digital signal processing.
Home-page: https://github.com/jpvantassel/signal-processing
Author: Joseph P. Vantassel
Author-email: jvantassel@utexas.edu
License: UNKNOWN
Project-URL: Bug Reports, https://github.com/jpvantassel/signal-processing/issues
Project-URL: Source, https://github.com/jpvantassel/signal-processing
Project-URL: Docs, https://sigpropy.readthedocs.io/en/latest/?badge=latest
Keywords: signal-processing signal
Platform: UNKNOWN
Classifier: Development Status :: 5 - Production/Stable
Classifier: Intended Audience :: Developers
Classifier: Intended Audience :: Education
Classifier: Intended Audience :: Science/Research
Classifier: Topic :: Education
Classifier: Topic :: Scientific/Engineering
Classifier: Topic :: Scientific/Engineering :: Physics
Classifier: License :: OSI Approved :: GNU General Public License v3 or later (GPLv3+)
Classifier: Programming Language :: Python :: 3.6
Classifier: Programming Language :: Python :: 3.7
Classifier: Programming Language :: Python :: 3.8
Classifier: Programming Language :: Python :: 3.9
Requires-Python: >=3.6
Requires-Dist: scipy
Requires-Dist: numpy
Requires-Dist: obspy
Requires-Dist: numba
Provides-Extra: dev
Requires-Dist: hypothesis ; extra == 'dev'
Requires-Dist: pandas ; extra == 'dev'
Requires-Dist: coverage ; extra == 'dev'
